aioowm/__init__.py
aioowm/aioowm.py
aioowm/const/__init__.py
aioowm/const/const.py
aioowm/handlers/__init__.py
aioowm/handlers/language.py
aioowm/handlers/response.py
aioowm/handlers/temperature.py
aioowm/http/__init__.py
aioowm/http/http.py
aioowm/types/__init__.py
aioowm/types/city.py
aioowm/types/model.py
aioowm/types/weather.py
aioowm-2.0.1.dist-info/LICENSE
aioowm-2.0.1.dist-info/METADATA
aioowm-2.0.1.dist-info/WHEEL
aioowm-2.0.1.dist-info/top_level.txt
aioowm-2.0.1.dist-info/RECORD
