Metadata-Version: 2.1
Name: aioowm
Version: 2.0.1
Summary: Async OpenWeatherMap API!
Home-page: https://github.com/vladislavkovalskyi/aioowm
Author: vladislavkovalskyi
Author-email: v.darknesssb@gmail.com
License: MIT
Platform: UNKNOWN
Classifier: Programming Language :: Python :: 3.6
Classifier: Programming Language :: Python :: 3.7
Classifier: Operating System :: OS Independent
Requires-Dist: aiohttp
Requires-Dist: pydantic
